ckanext_googleanalyticsbasic-0.2.0-nspkg.pth
ckanext/googleanalyticsbasic/plugin.py
ckanext/googleanalyticsbasic/tests/__init__.py
ckanext/googleanalyticsbasic/tests/test_plugin.py
ckanext/googleanalyticsbasic/tests/test_scripts_present.py
ckanext_googleanalyticsbasic-0.2.0.dist-info/METADATA
ckanext_googleanalyticsbasic-0.2.0.dist-info/WHEEL
ckanext_googleanalyticsbasic-0.2.0.dist-info/entry_points.txt
ckanext_googleanalyticsbasic-0.2.0.dist-info/namespace_packages.txt
ckanext_googleanalyticsbasic-0.2.0.dist-info/top_level.txt
ckanext_googleanalyticsbasic-0.2.0.dist-info/RECORD
