Metadata-Version: 2.1
Name: ckanext-googleanalyticsbasic
Version: 0.2.0
Summary: Basic extension to add google analytics tracking code in page header
Home-page: https://github.com/GSA/ckanext-googleanalyticsbasic
Author: Data.gov
Author-email: datagovhelp@gsa.gov
License: UNKNOWN
Platform: UNKNOWN
Classifier: Programming Language :: Python :: 3
